ognibuild-0.0.23.dist-info/WHEEL
ognibuild-0.0.23.dist-info/AUTHORS
ognibuild-0.0.23.dist-info/LICENSE
ognibuild-0.0.23.dist-info/top_level.txt
ognibuild-0.0.23.dist-info/entry_points.txt
ognibuild-0.0.23.dist-info/RECORD
ognibuild-0.0.23.dist-info/METADATA
ognibuild/upstream.py
ognibuild/vcs.py
ognibuild/__main__.py
ognibuild/buildsystem.py
ognibuild/__init__.py
ognibuild/buildlog_converters.py
ognibuild/requirements.py
ognibuild/py.typed
ognibuild/buildlog.py
ognibuild/build.py
ognibuild/test.py
ognibuild/dist.py
ognibuild/dep_server.py
ognibuild/dist_catcher.py
ognibuild/_ognibuild_rs.pyi
ognibuild/outputs.py
ognibuild/logs.py
ognibuild/fixers.py
ognibuild/_ognibuild_rs.cpython-312-i386-linux-gnu.so
ognibuild/info.py
ognibuild/clean.py
ognibuild/install.py
ognibuild/fix_build.py
ognibuild/debian/__init__.py
ognibuild/debian/build.py
ognibuild/debian/file_search.py
ognibuild/debian/apt.py
ognibuild/debian/udd.py
ognibuild/debian/build_deps.py
ognibuild/debian/upstream_deps.py
ognibuild/debian/fix_build.py
ognibuild/resolver/__init__.py
ognibuild/resolver/dep_server.py
ognibuild/resolver/apt.py
ognibuild/session/__init__.py
ognibuild/session/plain.py
ognibuild/session/schroot.py
ognibuild-0.0.23.data/scripts/report-apt-deps-status
